{
    "name": "TB_FP_BOR_SET_DTL",
    "useDefaultSchema": "N",
    "deletes": [ "TB_FP_BOR_SET_DTL" ],
    "columns": [
        {
            "name": "ID",
            "type": "ID",
            "update": "N"
        },
        {
            "name": "PLAN_SCOPE",
            "unique": "Y",
            "type": "STRING",
            "header": "PLAN_SCOPE"
        },
        {
            "name": "BOR_SET_CD",
            "unique": "Y",
            "type": "STRING",
            "header": "BOR_SET_CD"
        },
        {
            "name": "ROUTE_CD",
            "unique": "Y",
            "type": "STRING",
            "header": "ROUTE_CD"
        },
        {
            "name": "RESOURCE_CD",
            "unique": "Y",
            "type": "STRING",
            "header": "RESOURCE_CD"
        },
        {
            "name": "RESOURCE_TP_CD",
            "type": "STRING",
            "header": "RESOURCE_TP_CD"
        },
        {
            "name": "DESC_TXT",
            "type": "STRING",
            "header": "DESC_TXT"
        },
        {
            "name": "CREATED_BY",
            "type": "USER_ID",
            "update": "N"
        },
        {
            "name": "CREATED_AT",
            "type": "NOW",
            "update": "N"
        },
        {
            "name": "UPDATED_BY",
            "type": "USER_ID"
        },
        {
            "name": "UPDATED_AT",
            "type": "NOW"
        }
    ]
}
