{
    "name": "TB_FP_JC_TIME",
    "useDefaultSchema": "N",
    "deletes": [ "TB_FP_JC_TIME" ],
    "columns": [
        {
            "name": "ID",
            "type": "ID",
            "update": "N"
        },
        {
            "name": "PLAN_SCOPE",
            "unique": "Y",
            "type": "STRING",
            "header": "PLAN_SCOPE"
        },
        {
            "name": "RESOURCE_CD",
            "unique": "Y",
            "type": "STRING",
            "header": "RESOURCE_CD"
        },
        {
            "name": "PREV_ROUTE_CD",
            "unique": "Y",
            "type": "STRING",
            "header": "PREV_ROUTE_CD"
        },
        {
            "name": "NEXT_ROUTE_CD",
            "unique": "Y",
            "type": "STRING",
            "header": "NEXT_ROUTE_CD"
        },
        {
            "name": "PREV_JC_TIME",
            "type": "NUMBER",
            "header": "PREV_JC_TIME"
        },
        {
            "name": "NEXT_JC_TIME",
            "type": "NUMBER",
            "header": "NEXT_JC_TIME"
        },
        {
            "name": "TIME_UOM",
            "type": "STRING",
            "header": "TIME_UOM"
        },
        {
            "name": "JC_DIVIDE_TP_CD",
            "type": "STRING",
            "header": "JC_DIVIDE_TP_CD"
        },
        {
            "name": "CREATED_BY",
            "type": "USER_ID",
            "update": "N"
        },
        {
            "name": "CREATED_AT",
            "type": "NOW",
            "update": "N"
        },
        {
            "name": "UPDATED_BY",
            "type": "USER_ID"
        },
        {
            "name": "UPDATED_AT",
            "type": "NOW"
        }
    ]
}
